README.md
pyproject.toml
setup.py
src/pywarmup/__init__.py
src/pywarmup/api.py
src/pywarmup/error.py
src/pywarmup.egg-info/PKG-INFO
src/pywarmup.egg-info/SOURCES.txt
src/pywarmup.egg-info/dependency_links.txt
src/pywarmup.egg-info/requires.txt
src/pywarmup.egg-info/top_level.txt