Metadata-Version: 1.1
Name: pywarmup
Version: 0.1.0
Summary: Client library for Warmup thermostats
Home-page: https://github.com/lkollar/pywarmup
Author: Laszlo Kiss Kollar
Author-email: kiss.kollar.laszlo@gmail.com
License: Apache
Platform: UNKNOWN
Classifier: Intended Audience :: Developers
Classifier: License :: OSI Approved :: Apache Software License 
Classifier: Programming Language :: Python
Classifier: Programming Language :: Python :: 3
Classifier: Operating System :: OS Independent
Classifier: Topic :: Home Automation
Classifier: Topic :: Software Development :: Libraries
